My_pakage/__init__.py
My_pakage/module_1.py
calculationyash-0.1.0.dist-info/LICENSE
calculationyash-0.1.0.dist-info/METADATA
calculationyash-0.1.0.dist-info/WHEEL
calculationyash-0.1.0.dist-info/top_level.txt
calculationyash-0.1.0.dist-info/RECORD
