Metadata-Version: 2.1
Name: calculationyash
Version: 0.1.0
Summary: A pakage which can reverse text
Home-page: https://github.com/yash-sharma3/calculationyash
Author: Yash Sharma
Author-email: Yash Sharma <yash.innovater@gmail.com>
License: 
Requires-Python: >=3.6
License-File: LICENSE
